nlcx/__init__.py
nlcx/nlcx.py
nlcx/tests.py
Markdown_No_Lazy_Code_Extension-0.3.dist-info/LICENSE
Markdown_No_Lazy_Code_Extension-0.3.dist-info/METADATA
Markdown_No_Lazy_Code_Extension-0.3.dist-info/WHEEL
Markdown_No_Lazy_Code_Extension-0.3.dist-info/top_level.txt
Markdown_No_Lazy_Code_Extension-0.3.dist-info/RECORD
